jenti/__init__.py
jenti/patch.py
jenti-0.0.4.dist-info/LICENSE
jenti-0.0.4.dist-info/METADATA
jenti-0.0.4.dist-info/WHEEL
jenti-0.0.4.dist-info/top_level.txt
jenti-0.0.4.dist-info/RECORD
