Metadata-Version: 2.1
Name: jenti
Version: 0.0.4
Summary: To create/merge 2D or 3D patches.
Home-page: https://github.com/mrinal054/patch_and_merge
Author: Mrinal Kanti Dhar
Author-email: <mrinal054@gmail.com>
License: MIT
Keywords: python,patch,merge
Platform: UNKNOWN
Classifier: License :: OSI Approved :: MIT License
Classifier: Programming Language :: Python :: 3
Classifier: Operating System :: OS Independent
License-File: LICENSE
